README.md
pyproject.toml
setup.cfg
setup.py
src/causalImpactReturnSummary/__init__.py
src/causalImpactReturnSummary/analysis.py
src/causalImpactReturnSummary/inferences.py
src/causalImpactReturnSummary/misc.py
src/causalImpactReturnSummary/model.py
src/causalImpactReturnSummary.egg-info/PKG-INFO
src/causalImpactReturnSummary.egg-info/SOURCES.txt
src/causalImpactReturnSummary.egg-info/dependency_links.txt
src/causalImpactReturnSummary.egg-info/not-zip-safe
src/causalImpactReturnSummary.egg-info/requires.txt
src/causalImpactReturnSummary.egg-info/top_level.txt
src/causalimpactreturnsummary/__init__.py
src/causalimpactreturnsummary/analysis.py
src/causalimpactreturnsummary/inferences.py
src/causalimpactreturnsummary/misc.py
src/causalimpactreturnsummary/model.py
src/causalimpactreturnsummary.egg-info/PKG-INFO
src/causalimpactreturnsummary.egg-info/SOURCES.txt
src/causalimpactreturnsummary.egg-info/dependency_links.txt
src/causalimpactreturnsummary.egg-info/not-zip-safe
src/causalimpactreturnsummary.egg-info/requires.txt
src/causalimpactreturnsummary.egg-info/top_level.txt
tests/test_analysis.py
tests/test_inferences.py
tests/test_misc.py
tests/test_model.py